{
  "customer_id": "lr-ff-001",
  "generated_at": "2026-04-27T19:23:58.377326Z",
  "thread_summaries": [
    {
      "thread_id": "b95498618e9c85e1f35fee6f1e49ddfc",
      "date_start": "2025-10-30",
      "date_end": "2026-04-24",
      "participants": [
        "aditya.agarwal@elchemy.com",
        "ankit.singh@elchemy.com",
        "aroma@elchemy.com",
        "carlo.palmeri@lrindustries.it",
        "francesco.platania@lrindustries.it",
        "giorgia.ciaccio@lrindustries.it",
        "giovanni.lezzi@lrindustries.it",
        "giuliano.ursino@lrindustries.it",
        "jitesh.chauhan@elchemy.com",
        "lina.jadhav@elchemy.com",
        "michele.spadaro@lrindustries.it",
        "ops@elchemy.com",
        "ow@elchemy.com",
        "pina.saccone@lrindustries.it",
        "row@elchemy.com",
        "sebastiano.aiello@lrindustries.it"
      ],
      "summary": "Elchemy has provided CIF and DDP quotations for Diethyl Phthalate to the customer, Sebastiano. The customer requested a price reduction, and after discussions, multiple purchase orders (PO 638, PO 639, PO 640) were confirmed by Elchemy. The customer has amended the POs as requested.",
      "open_items": [
        "Elchemy to send Proforma Invoices for PO 638, PO 639, and PO 640",
        "Elchemy to confirm the dispatch planning details after Proforma Invoice acceptance"
      ],
      "sentiment": "positive",
      "key_products_discussed": [
        "Diethyl Phthalate"
      ]
    },
    {
      "thread_id": "0e33714df59d362ac3da3ead69698b62",
      "date_start": "2026-03-24",
      "date_end": "2026-04-23",
      "participants": [
        "aditya.agarwal@elchemy.com",
        "giorgia.ciaccio@lrindustries.it",
        "sebastiano.aiello@lrindustries.it"
      ],
      "summary": "Elchemy has been in discussions with LR Industries regarding a quotation for Benzaldehyde. After several exchanges, Elchemy provided a revised price of EUR 1.87/Kg CIF Augusta, but LR Industries is seeking a lower price of EUR 1.79 to finalize the order.",
      "open_items": [
        "LR Industries is awaiting a response from Elchemy regarding the price adjustment to EUR 1.79.",
        "Elchemy is considering the request for a lower price and has yet to confirm if they can meet it."
      ],
      "sentiment": "cooling",
      "key_products_discussed": [
        "Benzaldehyde"
      ]
    },
    {
      "thread_id": "3afac851fd340c27d519a25dc2085937",
      "date_start": "2026-04-20",
      "date_end": "2026-04-20",
      "participants": [
        "apurva.arora@elchemy.com",
        "sebastiano.aiello@lrindustries.it"
      ],
      "summary": "Apurva Arora from Elchemy has informed the customer that they will be out of the office and that their response will be delayed.",
      "open_items": [],
      "sentiment": "neutral",
      "key_products_discussed": []
    },
    {
      "thread_id": "11aa0e738c8627645306603b93487587",
      "date_start": "2026-04-17",
      "date_end": "2026-04-17",
      "participants": [
        "apurva.arora@elchemy.com",
        "sebastiano.aiello@lrindustries.it"
      ],
      "summary": "Apurva Arora from Elchemy informed the customer that they will be out of the office and that their response will be delayed. No specific products or commitments were discussed.",
      "open_items": [],
      "sentiment": "neutral",
      "key_products_discussed": []
    },
    {
      "thread_id": "9a1f8ece8891ee9e2df0723fa8623bfe",
      "date_start": "2026-04-14",
      "date_end": "2026-04-14",
      "participants": [
        "aditya.agarwal@elchemy.com",
        "sebastiano.aiello@lrindustries.it"
      ],
      "summary": "Elchemy discussed two order opportunities for Benzaldehyde and Diethyl Phthalate with the customer, including specific quantities and delivery dates. Revised price offers were shared, and feedback is requested to proceed further.",
      "open_items": [
        "Customer to provide feedback on revised price offers"
      ],
      "sentiment": "positive",
      "key_products_discussed": [
        "Benzaldehyde",
        "Diethyl Phthalate"
      ]
    },
    {
      "thread_id": "f964013a033163c459f485e9f924ee07",
      "date_start": "2026-02-03",
      "date_end": "2026-03-24",
      "participants": [
        "aditya.agarwal@elchemy.com",
        "sebastiano.aiello@lrindustries.it"
      ],
      "summary": "Elchemy followed up with Sebastiano regarding his upcoming requirements for various specialty chemicals, including Diethyl Phthalate, Benzaldehyde, and Benzyl Acetate. They are ready to discuss pricing and stock for these products and are eager to close some business.",
      "open_items": [
        "Sebastiano to confirm interest in Diethyl Phthalate, Benzyl Acetate, and Benzaldehyde for the next purchase"
      ],
      "sentiment": "positive",
      "key_products_discussed": [
        "Diethyl Phthalate",
        "Benzaldehyde",
        "Benzyl Acetate"
      ]
    },
    {
      "thread_id": "d584a779a580138245e38077bb18a392",
      "date_start": "2026-02-26",
      "date_end": "2026-03-16",
      "participants": [
        "aditya.agarwal@elchemy.com",
        "aroma@elchemy.com",
        "lina.jadhav@elchemy.com",
        "michele.spadaro@lrindustries.it",
        "ops@elchemy.com",
        "pina.saccone@lrindustries.it",
        "row@elchemy.com"
      ],
      "summary": "The email thread discusses the shipment of original documents for PO 1231, which is scheduled to be dispatched on March 2, 2026. Michele Spadaro requested the tracking number for the shipment, and Pina Saccone confirmed that the documents are expected to arrive at the Catania branch on March 11, 2026.",
      "open_items": [
        "Provide the tracking number for PO 1231"
      ],
      "sentiment": "positive",
      "key_products_discussed": []
    },
    {
      "thread_id": "229888114ee4f416c956dc0e479b7ff6",
      "date_start": "2026-02-26",
      "date_end": "2026-02-26",
      "participants": [
        "aditya.agarwal@elchemy.com",
        "sebastiano.aiello@lrindustries.it"
      ],
      "summary": "Elchemy is seeking L.R. Flavors & Fragrances to support their application for membership in the International Federation of Essential Oils and Aroma Trades (IFEAT) by acting as proposers. The email outlines the straightforward process involved in this request.",
      "open_items": [
        "Awaiting response from L.R. Flavors & Fragrances regarding their willingness to support Elchemy's IFEAT membership application"
      ],
      "sentiment": "positive",
      "key_products_discussed": []
    },
    {
      "thread_id": "43a8758c5789bbf3ef897a65e1a0f143",
      "date_start": "2026-02-26",
      "date_end": "2026-02-26",
      "participants": [
        "aditya.agarwal@elchemy.com",
        "pina.saccone@lrindustries.it"
      ],
      "summary": "The email thread discusses an error made by the bank regarding a SWIFT transaction. Pina Saccone from L.R. Flavours & Fragrances Industries apologized for the inconvenience and provided the relevant documentation, while Aditya Agarwal from Elchemy has involved the Accounts Team to address the issue further.",
      "open_items": [
        "Elchemy's Accounts Team to follow up with Pina regarding the SWIFT documentation"
      ],
      "sentiment": "neutral",
      "key_products_discussed": []
    },
    {
      "thread_id": "6b8e516f6b90b50b153e48c6b3c3b3c2",
      "date_start": "2026-02-05",
      "date_end": "2026-02-05",
      "participants": [
        "aditya.agarwal@elchemy.com",
        "giovanni.lezzi@lrindustries.it"
      ],
      "summary": "Elchemy is reaching out to Giovanni to discuss the opportunities arising from the recent India-EU Free Trade Agreement, which allows for duty-free access to aroma and fragrance ingredients. They aim to support Giovanni's growth in 2026 by leveraging their strengths in supply chain management and compliance.",
      "open_items": [
        "Schedule a 15-minute introductory call to discuss opportunities related to the new FTA"
      ],
      "sentiment": "positive",
      "key_products_discussed": [
        "aroma and fragrance ingredients",
        "high-quality aroma chemicals",
        "specialty ingredients"
      ]
    }
  ],
  "order_aggregate": {
    "customer_id": "lr-ff-001",
    "total_orders": 3,
    "total_value_ytd": 133862.40000000002,
    "last_order_date": "2026-04-22",
    "days_since_last_order": 6,
    "top_products": [
      {
        "name": "Diethyl Phthalate (DEP)",
        "qty": 80640.0,
        "value": 133862.40000000002,
        "last_ordered": "2026-04-22"
      }
    ],
    "inquiry_count": 0,
    "inquiry_to_order_rate": 0.0,
    "products_inquired_not_ordered": [],
    "open_order_products": [
      "Diethyl Phthalate (DEP)"
    ]
  },
  "filtered_news": [],
  "inquired_products": [
    {
      "name": "Di Ethyl Phthalate (DEP)",
      "deal_name": "L.R. Flavours & Fragrances - DEP (3 FCL) - Augusta (Italy)",
      "deal_stage": "1082127183",
      "deal_date": "2026-03-26",
      "quantity": 3.0,
      "is_open_deal": false
    },
    {
      "name": "Benzaldehyde (Almond Aldehyde) with CAS Number 100-52-7",
      "deal_name": "L.R. - Benzaldehyde (2 FCL) - Augusta (Italy)",
      "deal_stage": "1053511753",
      "deal_date": "2026-03-24",
      "quantity": 2.0,
      "is_open_deal": true
    },
    {
      "name": "Maltodextrin",
      "deal_name": "LR fragrance - Multiple - Augusta",
      "deal_stage": "2202102501",
      "deal_date": "2026-01-28",
      "quantity": 1.0,
      "is_open_deal": true
    },
    {
      "name": "Corn Starch",
      "deal_name": "LR fragrance - Multiple - Augusta",
      "deal_stage": "2202102501",
      "deal_date": "2026-01-28",
      "quantity": 1.0,
      "is_open_deal": true
    },
    {
      "name": "Arabic Gum",
      "deal_name": "LR fragrance - Multiple - Augusta",
      "deal_stage": "2202102501",
      "deal_date": "2026-01-28",
      "quantity": 1.0,
      "is_open_deal": true
    },
    {
      "name": "Silicon Dioxide",
      "deal_name": "LR fragrance - Multiple - Augusta",
      "deal_stage": "2202102501",
      "deal_date": "2026-01-28",
      "quantity": 1.0,
      "is_open_deal": true
    },
    {
      "name": "Sunflower Oil",
      "deal_name": "LR fragrance - Multiple - Augusta",
      "deal_stage": "2202102501",
      "deal_date": "2026-01-28",
      "quantity": 1.0,
      "is_open_deal": true
    },
    {
      "name": "Dextrose Monohydrate",
      "deal_name": "LR fragrance - Multiple - Augusta",
      "deal_stage": "2202102501",
      "deal_date": "2026-01-28",
      "quantity": 1.0,
      "is_open_deal": true
    },
    {
      "name": "2',3-dimethyl-3',4-dioxa-2,8-dithiabicyclo(3.3.0)octane spirocyclopentan",
      "deal_name": "L.R. Flavors & Fragrances - 2,3-dimethyl-3,4-dioxa-2,8-dithiabicyclo(3.3.0)octane spirocyclopentan Food Grade CAS: 38325-25-6 (10 GM) - Augusta (Italy)",
      "deal_stage": "1082127186",
      "deal_date": "2025-09-24",
      "quantity": 0.01,
      "is_open_deal": false
    },
    {
      "name": "Synthetic Vanillin",
      "deal_name": "L.R. Flavors & Fragrances - Synthetic Vanillin, Patchouli Dark Oil - Augusta (Italy)",
      "deal_stage": "1082127184",
      "deal_date": "2025-09-12",
      "quantity": 2000.0,
      "is_open_deal": false
    },
    {
      "name": "Patchouli Dark Oil",
      "deal_name": "L.R. Flavors & Fragrances - Synthetic Vanillin, Patchouli Dark Oil - Augusta (Italy)",
      "deal_stage": "1082127184",
      "deal_date": "2025-09-12",
      "quantity": 1400.0,
      "is_open_deal": false
    },
    {
      "name": "Orange Terpenes",
      "deal_name": "L.R. Flavors & Fragrances - Orange Terpenes (CAS:68647-72-3) - Augusta (Italy)",
      "deal_stage": "1082127184",
      "deal_date": "2025-09-08",
      "quantity": 20000.0,
      "is_open_deal": false
    }
  ]
}